mlops_cleaning.py
mlops_cleaning-0.1.0.dist-info/METADATA
mlops_cleaning-0.1.0.dist-info/WHEEL
mlops_cleaning-0.1.0.dist-info/top_level.txt
mlops_cleaning-0.1.0.dist-info/RECORD
