Metadata-Version: 2.1
Name: mlops-cleaning
Version: 0.1.0
Summary: UNKNOWN
Home-page: https://github.com/MerlijnDumarey/mlops-AI
Author: Merlijn Dumarey
Author-email: merlijn.dumarey@student.howest.be
License: UNKNOWN
Platform: UNKNOWN
Requires-Dist: h5py
Requires-Dist: pandas
Requires-Dist: numpy
Requires-Dist: scikit-learn
